README.md
setup.py
discord_wallet/wallet.py
discord_wallet.egg-info/PKG-INFO
discord_wallet.egg-info/SOURCES.txt
discord_wallet.egg-info/dependency_links.txt
discord_wallet.egg-info/requires.txt
discord_wallet.egg-info/top_level.txt