Metadata-Version: 2.1
Name: discord-wallet
Version: 0.3
Summary: Connect your bot to Discord Wallet.
Home-page: https://github.com/user/panicakr
Author: Panicakr
License: UNKNOWN
Download-URL: https://github.com/panicakr/discord_wallet/archive/v_01.tar.gz
Keywords: discord,discord.py,economy
Platform: UNKNOWN
Classifier: Development Status :: 5 - Production/Stable
Classifier: Intended Audience :: Developers
Classifier: Topic :: Software Development :: Build Tools
